{"first_name": "Debbie", "last_name": "Stabenow", "party": "Democrat", "state": "MI", "type": "sen", "twitter": "SenStabenow", "district": 0, "scorecard": {"blame": {"count": 226, "percent": 0.0841, "rank": 285.0, "sources": {"floor": {"count": 128, "percent": 0.0859}, "newsletters": {"count": null, "percent": null}, "statements": {"count": 19, "percent": 0.0}, "tweets": {"count": 79, "percent": 0.1013}}, "example": {"date": "", "source": "floor", "text": "Firearms are now the leading cause of death for American children and teens. Think about that: not car accidents, not cancer--guns."}}, "compromise": {"count": 226, "percent": 0.0398, "rank": 245.5, "sources": {"floor": {"count": 128, "percent": 0.0547}, "newsletters": {"count": null, "percent": null}, "statements": {"count": 19, "percent": 0.1053}, "tweets": {"count": 79, "percent": 0.0}}, "example": {"date": "", "source": "floor", "text": "Both Senator Peters and I are strong, strong supporters and thank President Biden for nominating him, and we look forward to colleagues joining us in a bipartisan vote, just as we had on the cloture vote, to make sure that he is confirmed today. Senator Peters and I were both honored to introduce him and his family during his hearing in the Judiciary Committee in November, and I know his family is so very proud of him--as we are."}}, "credit_claiming": {"count": 227, "percent": 0.1013, "rank": 241.0, "sources": {"floor": {"count": 128, "percent": 0.0547}, "newsletters": {"count": null, "percent": null}, "statements": {"count": 20, "percent": 0.15}, "tweets": {"count": 79, "percent": 0.1646}}, "example": {"date": "", "source": "tweets", "text": "Thanks to Democrats\u2019 historic investments, schools can hire more staff to support students struggling with mental health! [[url]]"}}, "insult": {"count": 226, "percent": 0.0044, "rank": 317.0, "sources": {"floor": {"count": 128, "percent": 0.0}, "newsletters": {"count": null, "percent": null}, "statements": {"count": 19, "percent": 0.0}, "tweets": {"count": 79, "percent": 0.0127}}, "example": {"date": "", "source": "tweets", "text": "Republicans are pushing our country closer to a first ever default based on dangerous extreme Maga politics. Stop! [[url]]"}}, "policy": {"count": 227, "percent": 0.3789, "rank": 419.0, "sources": {"floor": {"count": 128, "percent": 0.3828}, "newsletters": {"count": null, "percent": null}, "statements": {"count": 20, "percent": 0.4}, "tweets": {"count": 79, "percent": 0.3671}}, "example": {"date": "", "source": "tweets", "text": "Thanks to Democrats\u2019 historic investments, schools can hire more staff to support students struggling with mental health! [[url]]"}}, "foreign_policy": {"count": 227, "percent": 0.0044, "rank": 481.0, "sources": {"floor": {"count": 128, "percent": 0.0078}, "newsletters": {"count": null, "percent": null}, "statements": {"count": 20, "percent": 0.0}, "tweets": {"count": 79, "percent": 0.0}}, "example": {"date": "", "source": "floor", "text": "Some of my fondest memories with Matt are from our bipartisan 2019 codel to South Korea and Vietnam, organized by Senator Leahy. I will never forget standing at the DMZ with Matt and taking pictures with North Korean soldiers while they were taking pictures of us."}}, "legislative_discussion": {"count": 227, "percent": 0.1101, "rank": 497.0, "sources": {"floor": {"count": 128, "percent": 0.1641}, "newsletters": {"count": null, "percent": null}, "statements": {"count": 20, "percent": 0.1}, "tweets": {"count": 79, "percent": 0.0253}}, "example": {"date": "", "source": "floor", "text": "And while we are at it, let's close the gun show loophole and ensure that all gun sales in America require background checks. It is just common sense."}}}}