{"first_name": "Debbie", "last_name": "Wasserman Schultz", "party": "Democrat", "state": "FL", "type": "rep", "twitter": "RepDWStweets", "district": 25.0, "scorecard": {"blame": {"count": 33, "percent": 0.12313432835820895, "rank": 180.0, "sources": {"floor": {"count": 22, "percent": 0.12021857923497267}, "newsletters": {"count": 10, "percent": 0.12987012987012986}, "statements": {"count": null, "percent": null}, "tweets": {"count": 1, "percent": 0.125}}}, "compromise": {"count": 9, "percent": 0.033582089552238806, "rank": 263.0, "sources": {"floor": {"count": 6, "percent": 0.03278688524590164}, "newsletters": {"count": 2, "percent": 0.025974025974025976}, "statements": {"count": null, "percent": null}, "tweets": {"count": 1, "percent": 0.125}}}, "credit_claiming": {"count": 6, "percent": 0.022388059701492536, "rank": 446.0, "sources": {"floor": {"count": 2, "percent": 0.01092896174863388}, "newsletters": {"count": 4, "percent": 0.05194805194805195}, "statements": {"count": null, "percent": null}, "tweets": {"count": 0, "percent": 0.0}}}, "insult": {"count": 6, "percent": 0.022388059701492536, "rank": 151.0, "sources": {"floor": {"count": 5, "percent": 0.0273224043715847}, "newsletters": {"count": 1, "percent": 0.012987012987012988}, "statements": {"count": null, "percent": null}, "tweets": {"count": 0, "percent": 0.0}}}, "policy": {"count": 140, "percent": 0.5223880597014925, "rank": 167.5, "sources": {"floor": {"count": 107, "percent": 0.5846994535519126}, "newsletters": {"count": 31, "percent": 0.4025974025974026}, "statements": {"count": null, "percent": null}, "tweets": {"count": 2, "percent": 0.25}}}, "foreign_policy": {"count": 23, "percent": 0.08582089552238806, "rank": 161.0, "sources": {"floor": {"count": 23, "percent": 0.12568306010928962}, "newsletters": {"count": 0, "percent": 0.0}, "statements": {"count": null, "percent": null}, "tweets": {"count": 0, "percent": 0.0}}}, "legislative_discussion": {"count": 56, "percent": 0.208955223880597, "rank": 271.5, "sources": {"floor": {"count": 43, "percent": 0.23497267759562843}, "newsletters": {"count": 12, "percent": 0.15584415584415584}, "statements": {"count": null, "percent": null}, "tweets": {"count": 1, "percent": 0.125}}}}}